msms_compression/__init__.py
msms_compression/base_compressor.py
msms_compression/data_compressor.py
msms_compression/encoder.py
msms_compression/spectrum_compressor.py
msms_compression/utils.py
msms_compression-0.3.0.dist-info/METADATA
msms_compression-0.3.0.dist-info/WHEEL
msms_compression-0.3.0.dist-info/top_level.txt
msms_compression-0.3.0.dist-info/RECORD
