Metadata-Version: 2.1
Name: msms_compression
Version: 0.3.0
Summary: A tool for compressing MS/MS data
Author-email: Patrick Garrett <pgarrett@scripps.edu>
Classifier: Programming Language :: Python :: 3
Classifier: Development Status :: 4 - Beta
Classifier: License :: OSI Approved :: MIT License
Classifier: Operating System :: OS Independent
Requires-Python: >=3.8
Requires-Dist: brotli
Requires-Dist: lzstring
